examples/__init__.py
examples/product.py
odoo_client/__init__.py
odoo_client/client.py
odoo_client/decorators.py
odoo_client/model.py
odoo_client/object.py
odoo_client-0.0.6.dist-info/LICENSE
odoo_client-0.0.6.dist-info/METADATA
odoo_client-0.0.6.dist-info/WHEEL
odoo_client-0.0.6.dist-info/top_level.txt
odoo_client-0.0.6.dist-info/RECORD
