Metadata-Version: 2.1
Name: odoo-client
Version: 0.0.6
Summary: Simple API wrapper for Odoo's External API
Home-page: https://github.com/LNTW/odoo-python-api
Author: Michael Farwell
Author-email: mike@lie-nielsen.com
License: MIT
Keywords: python,odoo,api
Classifier: Development Status :: 3 - Alpha
Classifier: Intended Audience :: Developers
Classifier: License :: OSI Approved :: MIT License
Classifier: Natural Language :: English
Classifier: Programming Language :: Python :: 3
License-File: LICENSE
